sqlmodelx/__init__.py
sqlmodelx/enums.py
sqlmodelx/main.py
sqlmodelx/sqltypes.py
sqlmodelx-0.0.13.dist-info/WHEEL
sqlmodelx-0.0.13.dist-info/METADATA
sqlmodelx-0.0.13.dist-info/RECORD
