Metadata-Version: 2.1
Name: sqlmodelx
Version: 0.0.13
Summary: SQLModelX is an extension of the SQLModel library.
License: MIT
Keywords: sqlmodelx,sqlmodel,sqlalchemy,fastapi,fastapi-amis-admin
Author-email: atomi <1456417373@qq.com>
Requires-Python: >=3.7
Classifier: Environment :: Web Environment
Classifier: Framework :: FastAPI
Classifier: License :: OSI Approved :: Apache Software License
Classifier: Operating System :: OS Independent
Classifier: Programming Language :: Python :: 3
Classifier: Programming Language :: Python :: 3.10
Classifier: Programming Language :: Python :: 3.11
Classifier: Programming Language :: Python :: 3.8
Classifier: Programming Language :: Python :: 3.9
Classifier: Topic :: System :: Systems Administration
Requires-Dist: sqlmodel>=0.0.14
Provides-Extra: test
Requires-Dist: pytest>=7.1.3; extra == "test"
Project-URL: FastAPI-Amis-Admin, https://github.com/amisadmin/fastapi_amis_admin
Project-URL: Source, https://github.com/amisadmin/sqlmodelx
